[{"Warrior": ["Bone General 4&#9733;", "Nightmare Knight 4&#9733;", "Grumpy Corpse 4&#9733;"], "Assassin": ["Bonecarver 4&#9733;"], "Ranger": ["Lamb 4&#9733;", "Gbagbo 4&#9733;"], "Mage": ["Deathsworn 4&#9733;"], "Priest": ["Glen 4&#9733;"], "faction": "Shadow"}, {"Warrior": ["Kristian 4&#9733;", "Iron Bambi 4&#9733;", "Storm Huddle 4&#9733;"], "Assassin": ["Roy 4&#9733;"], "Ranger": ["LM-02 4&#9733;", "Liquor 4&#9733;"], "Mage": ["Sierra 4&#9733;", "Time Mage 4&#9733;"], "Priest": ["Sierra 4&#9733;", "Time Mage 4&#9733;"], "faction": "Fortress"}, {"Warrior": ["Immolatus 4&#9733;", "Lemegeton 4&#9733;", "Tanner 4&#9733;"], "Assassin": ["Akasha 4&#9733;"], "Ranger": ["Akasha 4&#9733;"], "Mage": ["Destroyer 4&#9733;", "Aleria 4&#9733;"], "Priest": ["Norma 4&#9733;", "Rogge 4&#9733;"], "faction": "Abyss"}, {"Warrior": ["Kargath 4&#9733;", "Chief 4&#9733;"], "Assassin": ["The Grey-eyed 4&#9733;", "Headstriker 4&#9733;"], "Ranger": ["Wind Walker 4&#9733;"], "Mage": ["Zekkis 4&#9733;", "Thale 4&#9733;", "Ent Elder 4&#9733;"], "Priest": ["Zekkis 4&#9733;", "Thale 4&#9733;", "Ent Elder 4&#9733;"], "faction": "Forest"}]